MANIFEST.in
README.md
build.gradle
gradlew
gradlew.bat
setup.cfg
setup.py
PyBoof.egg-info/PKG-INFO
PyBoof.egg-info/SOURCES.txt
PyBoof.egg-info/dependency_links.txt
PyBoof.egg-info/eager_resources.txt
PyBoof.egg-info/requires.txt
PyBoof.egg-info/top_level.txt
gradle/wrapper/gradle-wrapper.jar
gradle/wrapper/gradle-wrapper.properties
java/src/pyboof/BoofMemoryMapped.java
java/src/pyboof/FactoryPyBoofTemp.java
java/src/pyboof/FileIO.java
java/src/pyboof/PyBoofEntryPoint.java
java/test/pyboof/TestPyBoofEntryPoint.java
pyboof/PyBoof-all.jar
pyboof/__init__.py
pyboof/build_date.txt
pyboof/calib.py
pyboof/common.py
pyboof/feature.py
pyboof/flow.py
pyboof/geo.py
pyboof/image.py
pyboof/ip.py
pyboof/recognition.py
pyboof/sfm.py
pyboof/stereo.py
pyboof/swing.py
pyboof/version.txt
test/test_calib.py
test/test_common.py
test/test_feature.py
test/test_geo.py
test/test_image.py
test/test_ip.py
test/test_recognition.py
test/test_stereo.py