Metadata-Version: 2.1
Name: PyBoof
Version: 0.40.1
Summary: Py4J Python wrapper for BoofCV
Home-page: https://github.com/lessthanoptimal/PyBoof
Author: Peter Abeles
Author-email: peter.abeles@gmail.com
License: Apache 2.0
Platform: UNKNOWN
Classifier: Intended Audience :: Developers
Classifier: Programming Language :: Python :: 3.5
Requires-Python: >=3
